grypereport/__init__.py
grypereport/__main__.py
grypereport/__version__.py
grypereport/report.py
grypereport-0.0.17.dist-info/licenses/LICENSE
grypereport-0.0.17.dist-info/WHEEL
grypereport-0.0.17.dist-info/entry_points.txt
grypereport-0.0.17.dist-info/METADATA
grypereport-0.0.17.dist-info/RECORD
