Metadata-Version: 2.4
Name: grypereport
Version: 0.0.17
Summary: Grype vulnerability scanner report builder and CSV exporter.
Keywords: grype,report,builder,csv,csv-export,ci
Author: Alex Marienko
Author-email: Alex Marienko <alexey.maryenko@gmail.com>
License-Expression: MIT
License-File: LICENSE
Classifier: Programming Language :: Python :: 3
Classifier: Programming Language :: Python :: 3.11
Classifier: Programming Language :: Python :: 3.12
Classifier: Programming Language :: Python :: 3.13
Classifier: Programming Language :: Python :: 3 :: Only
Classifier: Environment :: Console
Classifier: Development Status :: 5 - Production/Stable
Classifier: License :: OSI Approved :: MIT License
Classifier: Natural Language :: English
Classifier: Operating System :: OS Independent
Classifier: Operating System :: POSIX
Classifier: Operating System :: POSIX :: Linux
Classifier: Operating System :: POSIX :: Other
Classifier: Operating System :: POSIX :: BSD
Classifier: Operating System :: Unix
Classifier: Operating System :: MacOS
Classifier: Operating System :: MacOS :: MacOS X
Requires-Dist: click>=8.3.0,<9
Requires-Dist: ftfy>=6.3 ; extra == 'encoding'
Requires-Python: >=3.11
Project-URL: github, https://github.com/amarienko/GrypeReport
Project-URL: homepage, https://github.com/amarienko/GrypeReport
Project-URL: issues, https://github.com/amarienko/GrypeReport/issues
Provides-Extra: encoding
